{"array": [{"gid": "custsvc", "users": [], "description": "custsvc", "permissions": [], "url": "/acs/api/v1/groups/custsvc"}, {"gid": "superusers", "users": [{"user": {"url": "/acs/api/v1/users/bootstrapuser", "is_service": false, "description": "Bootstrap superuser", "is_remote": false, "uid": "bootstrapuser"}, "membershipurl": "/acs/api/v1/groups/superusers/users/bootstrapuser"}], "description": "Superuser group", "permissions": [{"user": {"url": "/acs/api/v1/users/bootstrapuser", "is_service": false, "description": "Bootstrap superuser", "is_remote": false, "uid": "bootstrapuser"}, "membershipurl": "/acs/api/v1/groups/superusers/users/bootstrapuser"}], "url": "/acs/api/v1/groups/superusers"}, {"gid": "sales", "users": [{"user": {"url": "/acs/api/v1/users/jane.doe", "is_service": false, "description": "Jane Doe", "is_remote": false, "uid": "jane.doe"}, "membershipurl": "/acs/api/v1/groups/sales/users/jane.doe"}, {"user": {"url": "/acs/api/v1/users/frank.jones", "is_service": false, "description": "Frank Jones", "is_remote": false, "uid": "frank.jones"}, "membershipurl": "/acs/api/v1/groups/sales/users/frank.jones"}], "description": "sales", "permissions": [{"user": {"url": "/acs/api/v1/users/jane.doe", "is_service": false, "description": "Jane Doe", "is_remote": false, "uid": "jane.doe"}, "membershipurl": "/acs/api/v1/groups/sales/users/jane.doe"}, {"user": {"url": "/acs/api/v1/users/frank.jones", "is_service": false, "description": "Frank Jones", "is_remote": false, "uid": "frank.jones"}, "membershipurl": "/acs/api/v1/groups/sales/users/frank.jones"}], "url": "/acs/api/v1/groups/sales"}]}